maskedtensor/__init__.py
maskedtensor/binary.py
maskedtensor/core.py
maskedtensor/creation.py
maskedtensor/functions.py
maskedtensor/matmul.py
maskedtensor/passthrough.py
maskedtensor/reductions.py
maskedtensor/unary.py
maskedtensor/version.py
maskedtensor_nightly-0.12.dev2022714.dist-info/LICENSE
maskedtensor_nightly-0.12.dev2022714.dist-info/METADATA
maskedtensor_nightly-0.12.dev2022714.dist-info/WHEEL
maskedtensor_nightly-0.12.dev2022714.dist-info/top_level.txt
maskedtensor_nightly-0.12.dev2022714.dist-info/RECORD
