Metadata-Version: 2.1
Name: maskedtensor-nightly
Version: 0.12.dev2022714
Summary: MaskedTensors for PyTorch
Home-page: https://github.com/pytorch/maskedtensor
Author: PyTorch Team
Author-email: packages@pytorch.org
License: UNKNOWN
Platform: UNKNOWN
Classifier: Programming Language :: Python :: 3
Classifier: Operating System :: OS Independent
Requires-Python: >=3.7
License-File: LICENSE
Requires-Dist: torch (>1.12.0)
